pyisomme/__init__.py
pyisomme/__main__.py
pyisomme/calculate.py
pyisomme/channel.py
pyisomme/code.py
pyisomme/correlation.py
pyisomme/info.py
pyisomme/isomme.py
pyisomme/limits.py
pyisomme/parsing.py
pyisomme/plotting.py
pyisomme/unit.py
pyisomme/utils.py
pyisomme/report/__init__.py
pyisomme/report/criterion.py
pyisomme/report/page.py
pyisomme/report/report.py
pyisomme/report/euro_ncap/__init__.py
pyisomme/report/euro_ncap/euro_ncap.py
pyisomme/report/euro_ncap/frontal_50kmh.py
pyisomme/report/euro_ncap/frontal_mpdb.py
pyisomme/report/euro_ncap/limits.py
pyisomme/report/euro_ncap/side_barrier.py
pyisomme/report/euro_ncap/side_farside.py
pyisomme/report/euro_ncap/side_pole.py
pyisomme/report/iihs/limits.py
pyisomme/report/un/__init__.py
pyisomme/report/un/frontal_50kmh_r137.py
pyisomme/report/un/frontal_56kmh_odb_r94.py
pyisomme/report/un/limits.py
pyisomme/report/un/side_barrier_r95.py
pyisomme/report/un/side_pole_r135.py
pyisomme-0.0.3.data/data/docs/calculate.ipynb
pyisomme-0.0.3.data/data/docs/channel_diff_int.ipynb
pyisomme-0.0.3.data/data/docs/channel_filter.ipynb
pyisomme-0.0.3.data/data/docs/channel_operators.ipynb
pyisomme-0.0.3.data/data/docs/isomme_read.ipynb
pyisomme-0.0.3.data/data/docs/isomme_write.ipynb
pyisomme-0.0.3.data/data/docs/plotting.ipynb
pyisomme-0.0.3.data/data/docs/report.ipynb
pyisomme-0.0.3.data/data/docs/report.ipynb.pptx
pyisomme-0.0.3.dist-info/LICENSE
pyisomme-0.0.3.dist-info/METADATA
pyisomme-0.0.3.dist-info/WHEEL
pyisomme-0.0.3.dist-info/entry_points.txt
pyisomme-0.0.3.dist-info/top_level.txt
pyisomme-0.0.3.dist-info/RECORD
