Metadata-Version: 2.1
Name: pyisomme
Version: 0.0.3
Summary: Tools for ISO-MME file format (merge, report, calculate, CFC-filter, ...)
Author-email: Jonas Keller <jonaskeller14@googlemail.com>
License: MIT License
Project-URL: Homepage, https://github.com/jonaskeller14/pyisomme
Keywords: pyisomme,isomme,iso-mme,iso
Classifier: License :: OSI Approved :: MIT License
Classifier: Programming Language :: Python
Classifier: Programming Language :: Python :: 3
Requires-Python: >=3.9
License-File: LICENSE
Requires-Dist: matplotlib~=3.7.4
Requires-Dist: astropy~=6.0.0
Requires-Dist: pandas~=2.2.0
Requires-Dist: tqdm~=4.66.1
Requires-Dist: numpy~=1.26.3
Requires-Dist: scipy~=1.12.0
Requires-Dist: python-pptx~=0.6.23
Requires-Dist: setuptools~=58.1.0
Requires-Dist: dtwalign~=0.1.1
Provides-Extra: dev
Requires-Dist: objective-rating-metrics; extra == "dev"
